pi_inference/__init__.py
pi_inference/common.py
pi_inference/functions.py
pi_inference/sink/__init__.py
pi_inference/sink/factory.py
pi_inference/sink/pipeline.py
pi_inference/source/__init__.py
pi_inference/source/factory.py
pi_inference/source/pipeline.py
pi_inference-0.1.0.dist-info/LICENSE
pi_inference-0.1.0.dist-info/METADATA
pi_inference-0.1.0.dist-info/WHEEL
pi_inference-0.1.0.dist-info/top_level.txt
pi_inference-0.1.0.dist-info/RECORD
