Metadata-Version: 2.1
Name: pi-inference
Version: 0.1.0
Summary: pi-inference
Home-page: https://github.com/ethanlee928/pi-inference
Author: ethanlee
Author-email: ethan2000.el@gmail.com
License: UNKNOWN
Platform: UNKNOWN
Classifier: Programming Language :: Python :: 3
Classifier: License :: OSI Approved :: MIT License
Classifier: Operating System :: OS Independent
Requires-Python: >=3.8
Requires-Dist: PyGObject
Requires-Dist: ncnn
Requires-Dist: numpy
Requires-Dist: opencv-python
Requires-Dist: pycairo
Requires-Dist: supervision
Requires-Dist: typing-extensions
Provides-Extra: dev
Requires-Dist: black (==24.8.0) ; extra == 'dev'
Requires-Dist: flake8 ; extra == 'dev'
Requires-Dist: isort ; extra == 'dev'
Requires-Dist: pytest ; extra == 'dev'
Requires-Dist: twine ; extra == 'dev'
Requires-Dist: wheel ; extra == 'dev'
